{
  "project_info": {
    "project_number": "738650580646",
    "firebase_url": "https://moviews-b83b1.firebaseio.com",
    "project_id": "moviews-b83b1",
    "storage_bucket": "moviews-b83b1.appspot.com"
  },
  "client": [
    {
      "client_info": {
        "mobilesdk_app_id": "1:738650580646:android:c7d3ef8eee9b039f",
        "android_client_info": {
          "package_name": "digitalhouse.android.a0317moacns1c_02"
        }
      },
      "oauth_client": [
        {
          "client_id": "738650580646-da2fqrt3neo9chgh0a2si6l4hchav6o9.apps.googleusercontent.com",
          "client_type": 1,
          "android_info": {
            "package_name": "digitalhouse.android.a0317moacns1c_02",
            "certificate_hash": "55e585ee89075e4fa872073991230cf3938bf4dd"
          }
        },
        {
          "client_id": "738650580646-05nhqoan890ua1756q3mf4r35eltpqn2.apps.googleusercontent.com",
          "client_type": 3
        }
      ],
      "api_key": [
        {
          "current_key": "AIzaSyCI-mnoXBiUj0j4lTiom0GRsBAm8vVycdM"
        }
      ],
      "services": {
        "analytics_service": {
          "status": 1
        },
        "appinvite_service": {
          "status": 2,
          "other_platform_oauth_client": [
            {
              "client_id": "738650580646-05nhqoan890ua1756q3mf4r35eltpqn2.apps.googleusercontent.com",
              "client_type": 3
            }
          ]
        },
        "ads_service": {
          "status": 2
        }
      }
    }
  ],
  "configuration_version": "1"
}